xxjson/__init__.py
xxjson/__init__.pyi
xxjson/convert.c
xxjson/cxxjson.cp314t-win32.pyd
xxjson/module.c
xxjson/parser.pyx
xxjson/xxjson.h
xxjson/yyjson.c
xxjson/yyjson.h
xxjson-0.2.0.dist-info/METADATA
xxjson-0.2.0.dist-info/WHEEL
xxjson-0.2.0.dist-info/top_level.txt
xxjson-0.2.0.dist-info/RECORD
