Metadata-Version: 2.4
Name: xxjson
Version: 0.2.0
Summary: Simple wrapper around yyjson
Requires-Python: >=3.13
